{"is_source_file": true, "format": "JavaScript", "description": "A React hook implementation for managing a Three.js scene with an AirPods model, including setup, rendering, resize handling, and cleanup logic.", "external_files": ["./sceneSetup", "./constants", "./loadModel"], "external_methods": ["createRenderer", "createCamera", "createSceneWithLights", "resizeRendererToDisplaySize", "disposeSceneResources", "loadAirpodsModel"], "published": ["useThreeAirpods"], "classes": [], "methods": [{"name": "useThreeAirpods({ canvasRef, modelUrl = null } = {})", "description": "React hook to initialize and manage a Three.js scene with an AirPods model, handling setup, rendering loop, resize, and cleanup.", "scope": "", "scopeKind": ""}], "calls": ["createRenderer", "createSceneWithLights", "createCamera", "loadAirpodsModel", "resizeRendererToDisplaySize", "disposeSceneResources"], "search-terms": ["ReactThreeAirpodsHook", "three.js", "useCallback", "useRef", "useState", "SceneSetup", "AirpodsModel", "canvas resizing", "cleanup", "requestAnimationFrame"], "state": 2, "file_id": 17, "knowledge_revision": 39, "git_revision": "", "ctags": [{"_type": "tag", "name": "useThreeAirpods", "path": "/home/kavia/workspace/code-generation/airpods-max-showcase-176212-176221/web_frontend/src/three/useThreeAirpods.js", "pattern": "/^export function useThreeAirpods({ canvasRef, modelUrl = null } = {}) {$/", "language": "JavaScript", "kind": "function", "signature": "({ canvasRef, modelUrl = null } = {})"}], "hash": "e2e30719d3bc3bb9a37c9775b68ae5e2", "format-version": 4, "code-base-name": "web_frontend", "filename": "web_frontend/src/three/useThreeAirpods.js", "revision_history": [{"39": ""}]}